pandoc_tablenos.py
pandoc_tablenos-2.3.0.dist-info/AUTHORS
pandoc_tablenos-2.3.0.dist-info/LICENSE
pandoc_tablenos-2.3.0.dist-info/METADATA
pandoc_tablenos-2.3.0.dist-info/WHEEL
pandoc_tablenos-2.3.0.dist-info/entry_points.txt
pandoc_tablenos-2.3.0.dist-info/top_level.txt
pandoc_tablenos-2.3.0.dist-info/RECORD
